{
  "gitSyncId": "69952b18302bdb353697bdd7_2377c54d-1d5f-47f5-b3a1-e2a3348ce08c",
  "id": "Login_JSObject1.goToDashboard",
  "pluginId": "js-plugin",
  "pluginType": "JS",
  "unpublishedAction": {
    "actionConfiguration": {
      "encodeParamsToggle": true,
      "jsArguments": [],
      "paginationType": "NONE",
      "timeoutInMillisecond": 10000
    },
    "collectionId": "Login_JSObject1",
    "confirmBeforeExecute": false,
    "datasource": {
      "isAutoGenerated": false,
      "name": "UNUSED_DATASOURCE",
      "pluginId": "js-plugin"
    },
    "dynamicBindingPathList": [
      {
        "key": "body"
      }
    ],
    "fullyQualifiedName": "JSObject1.goToDashboard",
    "name": "goToDashboard",
    "pageId": "Login",
    "runBehaviour": "ON_PAGE_LOAD",
    "userSetOnLoad": true
  }
}