{
  "gitSyncId": "69952b18302bdb353697bdd7_0f2e2dd7-c985-4c33-8461-a9d6a78ae170",
  "id": "ApplyLeave_JSValidateLeave.b_submit_leaveonClick",
  "pluginId": "js-plugin",
  "pluginType": "JS",
  "unpublishedAction": {
    "actionConfiguration": {
      "encodeParamsToggle": true,
      "jsArguments": [],
      "paginationType": "NONE",
      "timeoutInMillisecond": 10000
    },
    "collectionId": "ApplyLeave_JSValidateLeave",
    "confirmBeforeExecute": false,
    "datasource": {
      "isAutoGenerated": false,
      "name": "UNUSED_DATASOURCE",
      "pluginId": "js-plugin"
    },
    "dynamicBindingPathList": [
      {
        "key": "body"
      }
    ],
    "fullyQualifiedName": "JSValidateLeave.b_submit_leaveonClick",
    "name": "b_submit_leaveonClick",
    "pageId": "ApplyLeave",
    "runBehaviour": "MANUAL",
    "userSetOnLoad": false
  }
}